AUTHORS.rst
CONTRIBUTING.rst
HISTORY.rst
LICENSE
MANIFEST.in
README.rst
setup.cfg
setup.py
docs/Makefile
docs/authors.rst
docs/conf.py
docs/contributing.rst
docs/history.rst
docs/index.rst
docs/installation.rst
docs/make.bat
docs/readme.rst
docs/usage.rst
pandasplexos/__init__.py
pandasplexos/cli.py
pandasplexos/pandasplexos.py
pandasplexos.egg-info/PKG-INFO
pandasplexos.egg-info/SOURCES.txt
pandasplexos.egg-info/dependency_links.txt
pandasplexos.egg-info/entry_points.txt
pandasplexos.egg-info/not-zip-safe
pandasplexos.egg-info/requires.txt
pandasplexos.egg-info/top_level.txt
tests/__init__.py
tests/test_pandasplexos.py